[
    {
        "Title": "HostsVN",
        "Source": "file:///home/runner/work/myfilterlist/myfilterlist/adblock/hostsvn.txt",
        "Base Output Filename": "hostsvn-{FORMAT}.txt",
        "Header": {
            "Last Modified": "2023-02-21T01:48:07.805Z",
            "Title": "HostsVN Compiled"
        },
        "Conversion": [
            [
                "Total Lines Processed",
                105812
            ],
            [
                "Comment Lines",
                6
            ],
            [
                "Empty Lines",
                6
            ],
            [
                "Non-Domain-only Rules Excluded",
                6
            ],
            [
                "Domain-only Rules Excluded (unsupported options)",
                0
            ],
            [
                "Domain-only Rules Excluded (exception conflict)",
                0
            ],
            [
                "Domain-only Rules Output",
                105800
            ]
        ],
        "Output Formats": {
            "Just Domains": "hostsvn-justdomains.txt"
        },
        "Domains Output": 105800
    },
    {
        "Title": "Lite list",
        "Source": "file:///home/runner/work/myfilterlist/myfilterlist/adblock/lite.txt",
        "Base Output Filename": "lite-{FORMAT}.txt",
        "Header": {
            "Last Modified": "2023-02-21T01:50:41.280Z",
            "Title": "Lite list"
        },
        "Conversion": [
            [
                "Total Lines Processed",
                586595
            ],
            [
                "Comment Lines",
                6
            ],
            [
                "Empty Lines",
                2602
            ],
            [
                "Non-Domain-only Rules Excluded",
                3132
            ],
            [
                "Domain-only Rules Excluded (unsupported options)",
                2
            ],
            [
                "Domain-only Rules Excluded (exception conflict)",
                44
            ],
            [
                "Domain-only Rules Output",
                583411
            ]
        ],
        "Output Formats": {
            "Just Domains": "lite-justdomains.txt"
        },
        "Domains Output": 583411
    },
    {
        "Title": "Full list",
        "Source": "file:///home/runner/work/myfilterlist/myfilterlist/adblock/filter.txt",
        "Base Output Filename": "filter-{FORMAT}.txt",
        "Header": {
            "Last Modified": "2023-02-21T01:52:41.727Z",
            "Title": "Full list"
        },
        "Conversion": [
            [
                "Total Lines Processed",
                628757
            ],
            [
                "Comment Lines",
                6
            ],
            [
                "Empty Lines",
                2613
            ],
            [
                "Non-Domain-only Rules Excluded",
                3139
            ],
            [
                "Domain-only Rules Excluded (unsupported options)",
                2
            ],
            [
                "Domain-only Rules Excluded (exception conflict)",
                45
            ],
            [
                "Domain-only Rules Output",
                625565
            ]
        ],
        "Output Formats": {
            "Just Domains": "filter-justdomains.txt"
        },
        "Domains Output": 625565
    },
    {
        "Title": "Extra list",
        "Source": "file:///home/runner/work/myfilterlist/myfilterlist/adblock/extra.txt",
        "Base Output Filename": "extra-{FORMAT}.txt",
        "Header": {
            "Last Modified": "2023-02-21T01:54:44.225Z",
            "Title": "Extra list"
        },
        "Conversion": [
            [
                "Total Lines Processed",
                566559
            ],
            [
                "Comment Lines",
                6
            ],
            [
                "Empty Lines",
                138
            ],
            [
                "Non-Domain-only Rules Excluded",
                439
            ],
            [
                "Domain-only Rules Excluded (unsupported options)",
                0
            ],
            [
                "Domain-only Rules Excluded (exception conflict)",
                0
            ],
            [
                "Domain-only Rules Output",
                566114
            ]
        ],
        "Output Formats": {
            "Just Domains": "extra-justdomains.txt"
        },
        "Domains Output": 566114
    },
    {
        "Title": "Cloudflare Zero Trust",
        "Source": "file:///home/runner/work/myfilterlist/myfilterlist/adblock/cf.txt",
        "Base Output Filename": "cloudflare-{FORMAT}.txt",
        "Header": {
            "Last Modified": "2023-02-21T01:53:04.976Z",
            "Title": "Cloudflare"
        },
        "Conversion": [
            [
                "Total Lines Processed",
                163555
            ],
            [
                "Comment Lines",
                6
            ],
            [
                "Empty Lines",
                10
            ],
            [
                "Non-Domain-only Rules Excluded",
                10
            ],
            [
                "Domain-only Rules Excluded (unsupported options)",
                0
            ],
            [
                "Domain-only Rules Excluded (exception conflict)",
                0
            ],
            [
                "Domain-only Rules Output",
                163539
            ]
        ],
        "Output Formats": {
            "Just Domains": "cloudflare-justdomains.txt"
        },
        "Domains Output": 163539
    }
]